rjpl/__init__.py
rjpl/classes.py
rjpl/constants.py
rjpl/methods.py
rjpl-0.3.6.dist-info/LICENSE
rjpl-0.3.6.dist-info/METADATA
rjpl-0.3.6.dist-info/WHEEL
rjpl-0.3.6.dist-info/top_level.txt
rjpl-0.3.6.dist-info/RECORD
